get_data.py
mem_watch.py
run_gadgetron_test.py
run_tests.py
stats_to_junit.py
gadgetron_integration_tests-0.0.5.dist-info/METADATA
gadgetron_integration_tests-0.0.5.dist-info/WHEEL
gadgetron_integration_tests-0.0.5.dist-info/entry_points.txt
gadgetron_integration_tests-0.0.5.dist-info/top_level.txt
gadgetron_integration_tests-0.0.5.dist-info/RECORD
